menataur/__init__.py
menataur/menataur.py
menataur/setup.py
menataur-1.1.dist-info/licenses/LICENSE
menataur-1.1.dist-info/METADATA
menataur-1.1.dist-info/WHEEL
menataur-1.1.dist-info/top_level.txt
menataur-1.1.dist-info/RECORD
