Metadata-Version: 2.4
Name: menataur
Version: 1.1
Summary: Menu Interface Builder for Python
Author-email: Gratonic <Gratonic@proton.me>
License-Expression: MIT
Project-URL: Homepage, https://github.com/Gratonic/Menataur
Project-URL: Issues, https://github.com/Gratonic/Menataur/issues
Classifier: Programming Language :: Python :: 3
Classifier: Operating System :: OS Independent
Requires-Python: >=3.8
License-File: LICENSE
Dynamic: license-file
